chkp_harmony_endpoint_management_sdk/__init__.py
chkp_harmony_endpoint_management_sdk/__init__template.py
chkp_harmony_endpoint_management_sdk/classes/__init__.py
chkp_harmony_endpoint_management_sdk/classes/harmony_api_exception.py
chkp_harmony_endpoint_management_sdk/classes/harmony_endpoint_saas_options.py
chkp_harmony_endpoint_management_sdk/classes/harmony_endpoint_sdk_info.py
chkp_harmony_endpoint_management_sdk/classes/infinity_portal_auth.py
chkp_harmony_endpoint_management_sdk/classes/internal.py
chkp_harmony_endpoint_management_sdk/classes/on_premise_portal_auth.py
chkp_harmony_endpoint_management_sdk/classes/sdk_connection_state.py
chkp_harmony_endpoint_management_sdk/core/__init__.py
chkp_harmony_endpoint_management_sdk/core/harmony_endpoint.py
chkp_harmony_endpoint_management_sdk/core/job_manager.py
chkp_harmony_endpoint_management_sdk/core/logger.py
chkp_harmony_endpoint_management_sdk/core/sdk_platform.py
chkp_harmony_endpoint_management_sdk/core/session_manager.py
chkp_harmony_endpoint_management_sdk/generated/__init__.py
chkp_harmony_endpoint_management_sdk/generated/cloud_README.md
chkp_harmony_endpoint_management_sdk/generated/saas_README.md
chkp_harmony_endpoint_management_sdk/generated/cloud/__init__.py
chkp_harmony_endpoint_management_sdk/generated/cloud/api_client.py
chkp_harmony_endpoint_management_sdk/generated/cloud/configuration.py
chkp_harmony_endpoint_management_sdk/generated/cloud/exceptions.py
chkp_harmony_endpoint_management_sdk/generated/cloud/rest.py
chkp_harmony_endpoint_management_sdk/generated/cloud/schemas.py
chkp_harmony_endpoint_management_sdk/generated/cloud/sdk_build.py
chkp_harmony_endpoint_management_sdk/generated/cloud/apis/__init__.py
chkp_harmony_endpoint_management_sdk/generated/cloud/apis/path_to_api.py
chkp_harmony_endpoint_management_sdk/generated/cloud/apis/tag_to_api.py
chkp_harmony_endpoint_management_sdk/generated/cloud/apis/paths/__init__.py
chkp_harmony_endpoint_management_sdk-1.2.2.dist-info/licenses/LICENSE
chkp_harmony_endpoint_management_sdk-1.2.2.dist-info/METADATA
chkp_harmony_endpoint_management_sdk-1.2.2.dist-info/WHEEL
chkp_harmony_endpoint_management_sdk-1.2.2.dist-info/top_level.txt
chkp_harmony_endpoint_management_sdk-1.2.2.dist-info/RECORD
