Metadata-Version: 2.4
Name: chkp-harmony-endpoint-management-sdk
Version: 1.2.2
Summary: Harmony Endpoint Official Python SDK
Home-page: https://github.com/CheckPointSW/harmony-endpoint-management-py-sdk
Author: Haim Kastner
Author-email: haimk@checkpoint.com
Maintainer: Haim Kastner
Maintainer-email: haimk@checkpoint.com
License: MIT
Keywords: python,harmony,endpoint,sdk,checkpoint
Requires-Python: >=3.8,<4.0
License-File: LICENSE
Requires-Dist: aenum~=3.1
Requires-Dist: certifi<2026.0,>=2024.0
Requires-Dist: charset-normalizer~=3.3
Requires-Dist: frozendict~=2.3
Requires-Dist: idna~=3.7
Requires-Dist: MarkupSafe~=2.1
Requires-Dist: python-dateutil~=2.8
Requires-Dist: python-dotenv~=1.0
Requires-Dist: requests~=2.32
Requires-Dist: typing-extensions~=4.9.0
Requires-Dist: pyjwt~=2.8
Requires-Dist: unitsnet-py>=0.1.82
Requires-Dist: urllib3~=2.2
Dynamic: author
Dynamic: author-email
Dynamic: description
Dynamic: description-content-type
Dynamic: home-page
Dynamic: keywords
Dynamic: license
Dynamic: license-file
Dynamic: maintainer
Dynamic: maintainer-email
Dynamic: requires-dist
Dynamic: requires-python
Dynamic: summary
